powerindex/__init__.py
powerindex/powerindex.py
powerindex/testpowerindex.py
powerindex-0.3.5.dist-info/LICENSE.txt
powerindex-0.3.5.dist-info/METADATA
powerindex-0.3.5.dist-info/WHEEL
powerindex-0.3.5.dist-info/entry_points.txt
powerindex-0.3.5.dist-info/top_level.txt
powerindex-0.3.5.dist-info/RECORD
