Metadata-Version: 2.1
Name: powerindex
Version: 0.3.5
Summary: python library to calculate power indices in weighted voting games
Home-page: http://gitlab.com/maxlit/powerindex
Author: Maxim Litvak
Author-email: maxim@litvak.eu
Keywords: power index,voting,Banzhaf,Shapley,Shubik,weighted voting game,game theory,political science,contested garment rule
Classifier: Development Status :: 3 - Alpha
Classifier: Environment :: Console
Classifier: Intended Audience :: Developers
Classifier: Intended Audience :: Science/Research
Classifier: Intended Audience :: Education
Classifier: License :: OSI Approved :: Python Software Foundation License
Classifier: Operating System :: MacOS :: MacOS X
Classifier: Operating System :: Microsoft :: Windows
Classifier: Operating System :: POSIX
Classifier: Programming Language :: Python
Classifier: Topic :: Education
Classifier: Topic :: Sociology
License-File: LICENSE.txt
